summd/__init__.py
summd/__main__.py
summd/generator.py
summd-0.1.0.dist-info/METADATA
summd-0.1.0.dist-info/WHEEL
summd-0.1.0.dist-info/entry_points.txt
summd-0.1.0.dist-info/RECORD
