Metadata-Version: 2.3
Name: summd
Version: 0.1.0
Summary: A CLI tool to bundle coding files into a single Markdown file.
License: MIT
Author: a-duty-rookie
Author-email: yutaro1127@gmail.com
Requires-Python: >=3.9
Classifier: License :: OSI Approved :: MIT License
Classifier: Programming Language :: Python :: 3
Classifier: Programming Language :: Python :: 3.9
Classifier: Programming Language :: Python :: 3.10
Classifier: Programming Language :: Python :: 3.11
Classifier: Programming Language :: Python :: 3.12
Classifier: Programming Language :: Python :: 3.13
Requires-Dist: nbformat (>=5.10.4,<6.0.0)
Requires-Dist: pathspec (>=0.12.1,<0.13.0)
